{
  "id": "robot-dynamics",
  "name": "机器人动力学",
  "stage": "阶段二：机器人学基础",
  "importance": "核心",
  "estimatedHours": 50,
  "description": "理解力、力矩与运动的关系，是控制器设计的物理基础。动力学方程 M(q)q̈+C(q,q̇)q̇+G(q)=τ 是计算力矩控制的核心。",
  "prerequisites": [
    "线性代数",
    "微积分与优化",
    "机器人运动学"
  ],
  "sections": [
    {
      "title": "Lagrange 力学",
      "content": "### 核心思想\n\n从能量角度推导运动方程，不需要分析约束力：\n$$L = T - V \\quad (\\text{动能} - \\text{势能})$$\n$$\\frac{d}{dt}\\frac{\\partial L}{\\partial \\dot{q}_i} - \\frac{\\partial L}{\\partial q_i} = \\tau_i$$\n\n得到标准形式：\n$$M(q)\\ddot{q} + C(q, \\dot{q})\\dot{q} + G(q) = \\tau$$\n\n- M(q)：质量矩阵（对称正定）\n- C(q,q̇)：科里奥利/离心力矩阵\n- G(q)：重力项\n\n```python\nimport numpy as np\nfrom sympy import *\n\n# 用 SymPy 推导 2-link 机械臂动力学\nq1, q2, dq1, dq2, ddq1, ddq2 = symbols('q1 q2 dq1 dq2 ddq1 ddq2')\nm1, m2, l1, l2, lc1, lc2, I1, I2, g_val = symbols('m1 m2 l1 l2 lc1 lc2 I1 I2 g', positive=True)\n\n# 质心位置\nx1 = lc1 * cos(q1)\ny1 = lc1 * sin(q1)\nx2 = l1 * cos(q1) + lc2 * cos(q1 + q2)\ny2 = l1 * sin(q1) + lc2 * sin(q1 + q2)\n\n# 质心速度\nvx1 = diff(x1, q1)*dq1\nvy1 = diff(y1, q1)*dq1\nvx2 = diff(x2, q1)*dq1 + diff(x2, q2)*dq2\nvy2 = diff(y2, q1)*dq1 + diff(y2, q2)*dq2\n\n# 动能\nT = Rational(1,2)*m1*(vx1**2+vy1**2) + Rational(1,2)*I1*dq1**2 + \\\n    Rational(1,2)*m2*(vx2**2+vy2**2) + Rational(1,2)*I2*(dq1+dq2)**2\n\n# 势能\nV = m1*g_val*y1 + m2*g_val*y2\n\n# Lagrangian\nL = expand(T - V)\nprint(\"Lagrangian 推导完成\")\n\n# 质量矩阵元素 M(q) 可以通过 T = 0.5 * dq^T M dq 提取\n```\n\n### Lagrange 力学 vs Newton-Euler 对比\n\n| 特性 | Lagrange | Newton-Euler |\n|------|:--------:|:------------:|\n| 方法论 | 能量法 | 力平衡法 |\n| 复杂度 | O(n³) | O(n) |\n| 推导难度 | 简单（标量能量）| 较难（向量力/力矩）|\n| 适合场景 | 理论分析、手推 | 实时计算、控制器 |\n| 输出 | M,C,G 矩阵 | 关节力矩 τ |\n| 约束力 | 自动消除 | 需要考虑 |\n\n### 动力学方程物理意义\n\n```\nM(q)q̈ + C(q,q̇)q̇ + G(q) = τ\n │        │           │      │\n │        │           │      └─ 外部力矩（电机输出）\n │        │           └─ 重力项（举着胳膊需要力矩）\n │        └─ 速度相关力（甩臂时的离心力/科氏力）\n └─ 惯性项（加速需要力矩=质量×加速度）\n\n类比开车:\n  M·加速度 = 发动机力 - 阻力 - 重力\n  M(q)q̈    = τ        - C·q̇  - G(q)\n```\n### 练习\n1. 手推 2-link 机械臂的完整 M, C, G 矩阵\n2. 用 SymPy 自动推导并验证手算结果\n3. 数值仿真：给定初始角度和零力矩，模拟自由摆动\n\n### 参考答案\n\n**1. 手推 2-link 机械臂的完整 M, C, G 矩阵**\n\n提示：结合本章的概念讲解和代码示例完成，核心步骤已在正文中详细说明。\n\n**2. 用 SymPy 自动推导并验证手算结果**\n\n提示：从定义出发，利用本章核心公式逐步推导。关键步骤已在概念讲解中覆盖。\n\n**3. 数值仿真：给定初始角度和零力矩，模拟自由摆动**\n\n提示：结合本章的概念讲解和代码示例完成，核心步骤已在正文中详细说明。\n"
    },
    {
      "title": "Newton-Euler 递推算法",
      "content": "### 算法思想\n\n正向递推（基座→末端）：计算每个连杆的速度/加速度\n反向递推（末端→基座）：计算每个关节的力/力矩\n\n计算复杂度 O(n)，比 Lagrange 法 O(n³) 高效，是实时控制器首选。\n\n```python\nimport numpy as np\n\ndef newton_euler_2link(q, dq, ddq, params):\n    \"\"\"2-link Newton-Euler 逆动力学\"\"\"\n    m1, m2, l1, l2, lc1, lc2, I1, I2, g = params\n    q1, q2 = q\n    dq1, dq2 = dq\n    ddq1, ddq2 = ddq\n    \n    # === 正向递推：计算加速度 ===\n    # 连杆1质心加速度\n    ax1 = -lc1*(ddq1*np.sin(q1) + dq1**2*np.cos(q1))\n    ay1 =  lc1*(ddq1*np.cos(q1) - dq1**2*np.sin(q1))\n    \n    # 连杆2质心加速度\n    ddq12 = ddq1 + ddq2\n    dq12 = dq1 + dq2\n    ax2 = -l1*(ddq1*np.sin(q1) + dq1**2*np.cos(q1)) \\\n          -lc2*(ddq12*np.sin(q1+q2) + dq12**2*np.cos(q1+q2))\n    ay2 =  l1*(ddq1*np.cos(q1) - dq1**2*np.sin(q1)) \\\n          +lc2*(ddq12*np.cos(q1+q2) - dq12**2*np.sin(q1+q2))\n    \n    # === 反向递推：计算力矩 ===\n    # 关节2力矩\n    tau2 = m2*(ax2*(-lc2*np.sin(q1+q2)) + (ay2+g)*lc2*np.cos(q1+q2)) + I2*ddq12\n    \n    # 关节1力矩\n    tau1 = m1*(ax1*(-lc1*np.sin(q1)) + (ay1+g)*lc1*np.cos(q1)) + I1*ddq1 \\\n         + m2*(ax2*(-l1*np.sin(q1)) + (ay2+g)*l1*np.cos(q1)) + tau2\n    \n    return np.array([tau1, tau2])\n\n# 参数：m1=1, m2=1, l1=1, l2=0.8, ...\nparams = (1, 1, 1, 0.8, 0.5, 0.4, 0.083, 0.053, 9.81)\ntau = newton_euler_2link([0.5, 0.3], [0.1, -0.2], [1.0, 0.5], params)\nprint(f\"关节力矩: {tau}\")\n```\n\n### 练习\n1. 实现通用 n-link 的 Newton-Euler 递推算法\n2. 用 Newton-Euler 计算重力补偿力矩 G(q)（令 dq=0, ddq=0）\n3. 对比 Lagrange 和 Newton-Euler 给出的力矩结果（应完全一致）\n\n### 参考答案\n\n**1. 实现通用 n-link 的 Newton-Euler 递推算法**\n\n```python\n# 参考本章代码示例修改即可\n# 核心步骤：\n# 1. 导入必要库\n# 2. 定义函数/类\n# 3. 运行验证\n# 详细实现见本章代码部分\n```\n\n**2. 用 Newton-Euler 计算重力补偿力矩 G(q)（令 dq=0, ddq=0）**\n\n提示：结合本章的概念讲解和代码示例完成，核心步骤已在正文中详细说明。\n\n**3. 对比 Lagrange 和 Newton-Euler 给出的力矩结果（应完全一致）**\n\n提示：分别运行两种方法，用相同输入数据对比输出结果（精度/速度/收敛性），以表格或图表展示差异。\n"
    },
    {
      "title": "动力学方程的性质",
      "content": "### M(q)q̈ + C(q,q̇)q̇ + G(q) = τ\n\n**M(q) 质量矩阵**\n- 对称正定：M = M^T, x^T M x > 0\n- 反映惯性：对角线 = 各关节的等效惯量\n- 非对角线 = 关节之间的耦合惯性\n\n**C(q,q̇) 科里奥利/离心力矩阵**\n- 速度相关的耦合力\n- Christoffel 符号：c_ijk = 0.5*(∂m_kj/∂q_i + ∂m_ki/∂q_j - ∂m_ij/∂q_k)\n\n**关键性质：Ṁ - 2C 是反对称矩阵**\n\n$$x^T(\\dot{M} - 2C)x = 0 \\quad \\forall x$$\n\n这表达了能量守恒：动力学系统无外力时总能量不变。这个性质在设计 Lyapunov 稳定性证明时至关重要。\n\n```python\nimport numpy as np\n\ndef dynamics_matrices_2link(q, dq, params):\n    \"\"\"计算 2-link 的 M, C, G 矩阵\"\"\"\n    m1, m2, l1, l2, lc1, lc2, I1, I2, g = params\n    q1, q2 = q\n    \n    # 质量矩阵\n    h = m2*l1*lc2*np.cos(q2)\n    M = np.array([\n        [m1*lc1**2 + m2*(l1**2 + lc2**2 + 2*l1*lc2*np.cos(q2)) + I1 + I2,\n         m2*(lc2**2 + l1*lc2*np.cos(q2)) + I2],\n        [m2*(lc2**2 + l1*lc2*np.cos(q2)) + I2,\n         m2*lc2**2 + I2]\n    ])\n    \n    # 科里奥利矩阵\n    C = np.array([\n        [-h*dq[1], -h*(dq[0]+dq[1])],\n        [h*dq[0], 0]\n    ])\n    \n    # 重力向量\n    G = np.array([\n        (m1*lc1 + m2*l1)*g*np.cos(q1) + m2*lc2*g*np.cos(q1+q2),\n        m2*lc2*g*np.cos(q1+q2)\n    ])\n    \n    return M, C, G\n\n# 验证 M 正定\nparams = (1, 1, 1, 0.8, 0.5, 0.4, 0.083, 0.053, 9.81)\nM, C, G = dynamics_matrices_2link([0.5, 0.3], [0.1, -0.2], params)\nprint(f\"M 特征值: {np.linalg.eigvalsh(M)}\")  # 都应为正\n```\n\n### M, C, G 矩阵速查\n\n| 矩阵 | 符号 | 维度 | 性质 | 物理意义 |\n|------|:----:|:----:|------|---------|\n| 质量矩阵 | M(q) | n×n | 对称正定 | 惯性/耦合 |\n| 科氏矩阵 | C(q,q̇) | n×n | Ṁ-2C 反对称 | 速度耦合力 |\n| 重力向量 | G(q) | n×1 | G=∂V/∂q | 重力补偿 |\n### 练习\n1. 数值验证 Ṁ-2C 的反对称性（用有限差分近似 Ṁ）\n2. 实现计算力矩控制器（Computed Torque Control）\n3. 模拟无外力的双摆运动，验证总能量守恒\n\n### 参考答案\n\n**1. 数值验证 Ṁ-2C 的反对称性（用有限差分近似 Ṁ）**\n\n提示：结合本章的概念讲解和代码示例完成，核心步骤已在正文中详细说明。\n\n**2. 实现计算力矩控制器（Computed Torque Control）**\n\n```python\n# 参考本章代码示例修改即可\n# 核心步骤：\n# 1. 导入必要库\n# 2. 定义函数/类\n# 3. 运行验证\n# 详细实现见本章代码部分\n```\n\n**3. 模拟无外力的双摆运动，验证总能量守恒**\n\n提示：结合本章的概念讲解和代码示例完成，核心步骤已在正文中详细说明。\n"
    },
    {
      "title": "接触力学基础",
      "content": "### 刚性接触 vs 柔性接触\n\n- **刚性接触**：接触面不可穿透，用约束方程处理。线性互补问题 (LCP)\n- **柔性接触**（Spring-Damper）：允许微小穿透，接触力 = k·δ + d·δ̇。MuJoCo 用的就是柔性模型\n\n### 摩擦锥模型（库仑摩擦）\n\n$$|f_t| \\leq \\mu \\cdot f_n$$\n\n切向摩擦力不超过 μ 倍法向力。3D 中摩擦锥是一个圆锥，常用多面体近似（线性化后变成线性约束）。\n\n### 抓取力分析\n\n力闭合（Force Closure）：无论外力从哪个方向来，手指都能产生平衡的力。\n\n```python\nimport numpy as np\n\ndef check_force_closure_2d(contacts, normals, mu=0.5):\n    \"\"\"2D 简化力闭合检查\n    contacts: 接触点位置 (n, 2)\n    normals: 接触法向量 (n, 2)，指向物体内部\n    mu: 摩擦系数\n    \"\"\"\n    wrenches = []\n    for pos, normal in zip(contacts, normals):\n        # 法向力方向\n        fn = normal\n        # 摩擦力方向（切向）\n        tangent = np.array([-normal[1], normal[0]])\n        \n        # 摩擦锥的两个边界\n        f1 = fn + mu * tangent\n        f2 = fn - mu * tangent\n        \n        # 力矩 = r × f（2D 简化为标量）\n        for f in [f1, f2]:\n            wrench = np.array([f[0], f[1], pos[0]*f[1] - pos[1]*f[0]])\n            wrenches.append(wrench)\n    \n    # 检查凸包是否包含原点（简化判断）\n    W = np.array(wrenches)\n    # 如果所有 wrench 的凸组合能覆盖任意方向，则力闭合\n    print(f\"Wrench 矩阵形状: {W.shape}\")\n    return W\n\n# 两指平行抓取\ncontacts = np.array([[0, 0.05], [0, -0.05]])  # 上下两个接触点\nnormals = np.array([[0, -1], [0, 1]])  # 法向量指向物体中心\nW = check_force_closure_2d(contacts, normals, mu=0.5)\nprint(f\"Wrench 空间:\\n{W}\")\n```\n\n### MuJoCo 中的接触模型\n\nMuJoCo 使用软接触模型+凸优化求解接触力：\n- `solref`：弹簧刚度和阻尼参数\n- `solimp`：摩擦锥参数\n- 接触力通过求解 QP 得到\n\n### 练习\n1. 实现 2D 圆柱抓取的摩擦锥分析，判断不同接触位置是否力闭合\n2. 用 MuJoCo 搭建一个简单抓取场景，观察接触力的变化\n3. 实现弹簧-阻尼接触模型，模拟球体落地弹跳\n\n### 参考答案\n\n**1. 实现 2D 圆柱抓取的摩擦锥分析，判断不同接触位置是否力闭合**\n\n```python\n# 参考本章代码示例修改即可\n# 核心步骤：\n# 1. 导入必要库\n# 2. 定义函数/类\n# 3. 运行验证\n# 详细实现见本章代码部分\n```\n\n**2. 用 MuJoCo 搭建一个简单抓取场景，观察接触力的变化**\n\n提示：结合本章的概念讲解和代码示例完成，核心步骤已在正文中详细说明。\n\n**3. 实现弹簧-阻尼接触模型，模拟球体落地弹跳**\n\n```python\n# 参考本章代码示例修改即可\n# 核心步骤：\n# 1. 导入必要库\n# 2. 定义函数/类\n# 3. 运行验证\n# 详细实现见本章代码部分\n```\n"
    }
  ],
  "resources": [
    {
      "name": "Featherstone《Rigid Body Dynamics Algorithms》",
      "url": "https://link.springer.com/book/10.1007/978-1-4899-7560-7",
      "type": "教材",
      "description": "刚体动力学算法圣经，Newton-Euler 递推、RNEA、ABA 的权威参考。"
    },
    {
      "name": "Modern Robotics Ch8 (Dynamics)",
      "url": "http://hades.mech.northwestern.edu/images/7/7f/MR.pdf",
      "type": "教材",
      "description": "Modern Robotics 动力学章节，Lagrange 方法推导非常清晰。免费 PDF。"
    },
    {
      "name": "MuJoCo 文档 (Contact Model)",
      "url": "https://mujoco.readthedocs.io/en/stable/computation/index.html",
      "type": "文档",
      "description": "MuJoCo 的物理计算文档，详细解释接触模型和求解算法。"
    },
    {
      "name": "Pinocchio 动力学库",
      "url": "https://stack-of-tasks.github.io/pinocchio/",
      "type": "工具",
      "description": "高效的机器人动力学 C++/Python 库，支持 RNEA、ABA、CRBA 等算法。"
    },
    {
      "name": "Featherstone 动力学算法讲座",
      "url": "https://www.youtube.com/results?search_query=featherstone+rigid+body+dynamics+lecture",
      "type": "视频",
      "description": "刚体动力学算法权威讲解，Newton-Euler 递推和 ABA 算法。"
    }
  ],
  "weeklyPlan": "**第1周**：Lagrange 力学推导 2-link 动力学\n**第2周**：Newton-Euler 递推算法实现\n**第3周**：M/C/G 矩阵的物理意义和性质验证\n**第4周**：接触力学 + MuJoCo 仿真验证"
}