{
  "title": "结构设计与快速原型",
  "lastUpdated": "2026-04-21T18:42",
  "content": "### 从CAD到实物：机器人结构设计全流程\n\n机器人不只是电机+传感器——它们需要**结构件**来承载、连接和保护这些元器件。结构设计决定了机器人的重量、刚度、精度和成本。\n\n### 结构设计的核心考量\n\n| 维度 | 关键指标 | 设计取舍 |\n|------|---------|--------|\n| **刚度** | 变形量(mm) | 刚度↑ → 重量↑ |\n| **重量** | 连杆质量(g) | 轻量化 → 刚度↓/成本↑ |\n| **精度** | 重复定位(mm) | 精度↑ → 加工成本↑ |\n| **成本** | 单件成本(¥) | 原型快速迭代 vs 批量生产 |\n| **可维护性** | 拆装时间(min) | 模块化设计更好维护 |\n\n### 常用材料对比\n\n| 材料 | 密度(g/cm³) | 刚度 | 成本 | 加工方式 | 适用 |\n|------|:---------:|:---:|:---:|---------|------|\n| 铝合金6061 | 2.7 | 高 | 中 | CNC加工 | 关键承力件 |\n| 铝合金7075 | 2.8 | 很高 | 高 | CNC加工 | 高精度关节 |\n| PLA/PETG | 1.24 | 低 | 很低 | 3D打印(FDM) | 快速原型/外壳 |\n| 尼龙PA12 | 1.01 | 中 | 中 | 3D打印(SLS) | 功能件 |\n| 碳纤维板 | 1.6 | 极高 | 高 | CNC切割 | 轻量化臂板 |\n| 钢(45#) | 7.85 | 极高 | 低 | 车铣 | 轴/齿轮 |\n\n### 3D 打印在机器人中的应用\n\n3D 打印（增材制造）彻底改变了机器人原型开发的节奏：\n\n```\n传统制造流程:\n  CAD设计 → 图纸 → 找工厂报价 → 等待加工(7-14天) → 装配测试\n  一轮迭代: 2-3周, ¥500-5000/次\n\n3D打印流程:\n  CAD设计 → 切片 → 打印(3-12小时) → 装配测试\n  一轮迭代: 1天, ¥10-50/次\n  → 可以一天迭代多个版本!\n```\n\n**哪些零件适合3D打印:**\n- ✅ 外壳/护罩（不承力）\n- ✅ 传感器支架/相机安装座\n- ✅ 快速验证的机械臂连杆\n- ✅ 夹爪手指（PLA/TPU柔性）\n- ❌ 高精度轴承座（尺寸公差不够）\n- ❌ 高扭矩传动齿轮（强度不够）\n- ❌ 长期承受交变载荷的零件（疲劳）\n\n### FDM 3D 打印参数指南\n\n| 参数 | 推荐值 | 说明 |\n|------|:-----:|------|\n| 层高 | 0.2mm | 通用值; 0.1mm精细件 |\n| 填充率 | 20-40% | 功能件用40%+; 展示件20% |\n| 壁厚 | 3-4层 | 承力件用4+层 |\n| 材料 | PETG | 比PLA更耐用; TPU柔性件 |\n| 支撑 | 树状 | 减少支撑痕迹 |\n| 打印方向 | 载荷⊥层线 | 层间是最弱方向 |\n\n### CAD 工具选型\n\n| 工具 | 类型 | 成本 | 学习曲线 | 适用 |\n|------|------|:---:|:------:|------|\n| Onshape | 云端参数化 | 免费(教育) | 中 | 团队协作首选 |\n| Fusion 360 | 桌面参数化 | 免费(个人) | 中 | 个人项目 |\n| SolidWorks | 桌面参数化 | ¥5万+/年 | 高 | 工业级 |\n| FreeCAD | 开源桌面 | 免费 | 中高 | 预算为零 |\n| Blender | 多边形建模 | 免费 | 高 | 外观设计/仿真 |\n\n### URDF/MJCF 与 CAD 的关系\n\n```\nCAD 设计 (SolidWorks/Fusion 360)\n    ↓ 导出 STL/DAE 网格\n    ↓ 测量质量/惯量/关节位置\nURDF/MJCF 描述文件\n    ├── visual: 用 STL 渲染外观\n    ├── collision: 简化碰撞体(box/cylinder)\n    ├── inertial: 质量+质心+惯量矩阵\n    └── joint: 关节类型+限位+阻尼\n\n工具:\n  sw_urdf_exporter (SolidWorks → URDF)\n  fusion2urdf (Fusion 360 → URDF)\n  onshape-to-robot (Onshape → URDF)\n```\n\n### 设计案例: reBot Arm B601 开源机械臂\n\n2026年4月 Seeed Studio 发布的 reBot Arm B601 是结构设计开源的典范:\n\n```\n开源内容:\n├── 完整 STEP 文件 (每个零件的3D模型)\n├── BOM 清单 (精确到每颗螺丝的型号和购买链接)\n├── 装配指南 (图文+视频)\n├── 电路原理图\n└── 3D 打印零件 STL\n\n结构特点:\n- 6+1 DOF, 650mm 臂展, 1.5kg 负载\n- 铝合金+3D打印混合结构\n- 达妙电机(DM)和Robostride(RS)两个版本\n- 总成本 ~$1200\n```\n\n### 练习\n1. 用 Fusion 360 或 Onshape 设计一个简单的2-DOF机械臂连杆，导出 STL 并3D打印\n2. 对比PLA和PETG打印件在抓取力测试下的变形量\n3. 从 CAD 导出 URDF: 安装 fusion2urdf 插件，为你的设计生成 URDF 并在 RViz 中可视化\n\n### 参考答案\n\n**1. 2-DOF 机械臂连杆设计要点**\n\n```python\nimport numpy as np\n\ndef link_design_calculator():\n    \"\"\"机械臂连杆结构设计计算器\"\"\"\n    # 设计参数\n    payload_kg = 0.5      # 负载\n    link_length_m = 0.20  # 连杆长度\n    safety_factor = 3.0   # 安全系数\n    g = 9.81\n    \n    # 最大弯矩 (悬臂梁, 末端集中载荷)\n    M_max = payload_kg * g * link_length_m * safety_factor  # Nm\n    \n    # 材料选择\n    materials = {\n        'PLA':   {'sigma_y': 50e6, 'E': 3.5e9, 'rho': 1240},  # Pa, Pa, kg/m³\n        'PETG':  {'sigma_y': 45e6, 'E': 2.0e9, 'rho': 1270},\n        'Al6061':{'sigma_y': 275e6,'E': 69e9,  'rho': 2700},\n        'Nylon': {'sigma_y': 75e6, 'E': 2.7e9, 'rho': 1010},\n    }\n    \n    print('=== 连杆截面设计 ===')\n    print(f'负载: {payload_kg}kg, 臂长: {link_length_m*100}cm')\n    print(f'最大弯矩: {M_max:.2f} Nm (安全系数{safety_factor}x)')\n    print(f'\\n{\"材料\":>8} | {\"最小壁厚\":>8} | {\"变形量\":>8} | {\"连杆质量\":>8}')\n    print('-' * 42)\n    \n    for name, props in materials.items():\n        # 方形截面, 外径20mm, 求最小壁厚\n        b_outer = 0.02  # 20mm 外径\n        # M/S = sigma_y, S = b*h²/6 (方形截面)\n        S_min = M_max / props['sigma_y']  # 最小截面模量\n        # S = b*h²/6, 近似 h = b = t (壁厚)\n        t_min = (6 * S_min / b_outer) ** 0.5\n        t_min = max(t_min, 0.002)  # 最小2mm壁厚\n        \n        # 变形量 (悬臂梁末端挠度)\n        I = b_outer * t_min**3 / 12  # 惯性矩(简化)\n        deflection = payload_kg * g * link_length_m**3 / (3 * props['E'] * I)\n        \n        # 质量\n        volume = b_outer * t_min * link_length_m  # 简化\n        mass = volume * props['rho']\n        \n        print(f'{name:>8} | {t_min*1000:>6.1f}mm | {deflection*1000:>6.2f}mm | {mass*1000:>6.0f}g')\n    \n    print('\\n结论:')\n    print('  PLA: 壁厚大、变形大 → 只适合原型验证')\n    print('  Al6061: 壁薄、刚度高 → 正式版首选')\n    print('  PETG: 比PLA好一点 → 3D打印功能件')\n\nlink_design_calculator()\n```\n\n**2. PLA vs PETG 强度对比**\n\n```python\nimport numpy as np\n\ndef material_comparison():\n    \"\"\"3D打印材料力学性能对比\"\"\"\n    tests = [\n        ('PLA',  50, 3.5, 1.24, '脆性断裂,精度好'),\n        ('PETG', 45, 2.0, 1.27, '韧性好,略软'),\n        ('ABS',  40, 2.1, 1.04, '耐温,需要机箱'),\n        ('TPU',  15, 0.03, 1.21, '柔性,适合夹爪垫'),\n        ('PA(尼龙)', 75, 2.7, 1.01, '最强,SLS打印'),\n    ]\n    print('=== 3D打印材料对比 ===')\n    print(f'{\"材料\":>10} | {\"抗拉(MPa)\":>10} | {\"模量(GPa)\":>10} | {\"特点\"}')\n    print('-' * 55)\n    for name, strength, modulus, density, note in tests:\n        print(f'{name:>10} | {strength:>10} | {modulus:>10.1f} | {note}')\n    \n    print('\\n推荐:')\n    print('  原型验证 → PLA (便宜、精度好、打印容易)')\n    print('  功能件   → PETG (韧性好、不易裂)')\n    print('  夹爪垫   → TPU (柔性、防滑)')\n    print('  最终版   → CNC铝合金 (刚度+精度)')\n\nmaterial_comparison()\n```\n\n**3. CAD → URDF 导出步骤**\n\n```bash\n# Fusion 360 → URDF 流程\n# 1. 安装 fusion2urdf 插件\n# https://github.com/syuntoku14/fusion2urdf\n\n# 2. 在 Fusion 360 中:\n#    - 定义关节(Joint): 每个旋转/移动关节\n#    - 设置材料属性(自动计算质量/惯量)\n#    - 运行 fusion2urdf 脚本\n\n# 3. 输出:\n# my_robot/\n# ├── urdf/my_robot.urdf\n# ├── meshes/\n# │   ├── base_link.stl\n# │   ├── link1.stl\n# │   └── link2.stl\n# └── launch/display.launch.py\n\n# 4. 在 RViz 中验证:\n# ros2 launch my_robot display.launch.py\n\nprint('CAD → URDF 工具链:')\nprint('  Fusion 360: fusion2urdf (GitHub)')\nprint('  Onshape:    onshape-to-robot (pip install onshape-to-robot)')\nprint('  SolidWorks: sw_urdf_exporter (官方插件)')\nprint('\\n关键: URDF中的 inertial 参数必须准确,否则仿真不真实')\n```\n"
}